.gitignore
MANIFEST.in
README.rst
base.cfg
bootstrap.py
buildout.cfg
setup.cfg
setup.py
test-4.0.x.cfg
test-4.1.x.cfg
test-4.2.x.cfg
test-4.3.x.cfg
.cache/.empty
docs/CHANGES.rst
docs/INSTALL.txt
docs/LICENSE.GPL
docs/LICENSE.txt
src/__init__.py
src/collective/__init__.py
src/collective.cron.egg-info/PKG-INFO
src/collective.cron.egg-info/SOURCES.txt
src/collective.cron.egg-info/dependency_links.txt
src/collective.cron.egg-info/entry_points.txt
src/collective.cron.egg-info/namespace_packages.txt
src/collective.cron.egg-info/requires.txt
src/collective.cron.egg-info/top_level.txt
src/collective/cron/__init__.py
src/collective/cron/configure.zcml
src/collective/cron/crontab.py
src/collective/cron/events.py
src/collective/cron/interfaces.py
src/collective/cron/profiles.zcml
src/collective/cron/rebuild_i18n.sh
src/collective/cron/setuphandlers.py
src/collective/cron/skins.zcml
src/collective/cron/testing.py
src/collective/cron/timed_api.rst
src/collective/cron/timed_genericsetup.rst
src/collective/cron/timed_webui.rst
src/collective/cron/uninstall.rst
src/collective/cron/utils.py
src/collective/cron/Extensions/Install.py
src/collective/cron/Extensions/__init__.py
src/collective/cron/adapters/__init__.py
src/collective/cron/adapters/configure.zcml
src/collective/cron/adapters/exportimport.py
src/collective/cron/adapters/manager.py
src/collective/cron/adapters/ploneappasync.py
src/collective/cron/adapters/ploneappasync.zcml
src/collective/cron/adapters/registry.py
src/collective/cron/adapters/registry.zcml
src/collective/cron/adapters/utils.py
src/collective/cron/browser/__init__.py
src/collective/cron/browser/configure.zcml
src/collective/cron/browser/controlpanel.py
src/collective/cron/browser/cpanelformwrapper.pt
src/collective/cron/browser/cron.pt
src/collective/cron/browser/crontab.pt
src/collective/cron/browser/interfaces.py
src/collective/cron/browser/kss.py
src/collective/cron/locales/collective.cron-manual.pot
src/collective/cron/locales/collective.cron.pot
src/collective/cron/locales/fr/LC_MESSAGES/collective.cron.po
src/collective/cron/profiles/default/browserlayer.xml
src/collective/cron/profiles/default/collectivecron_various.txt
src/collective/cron/profiles/default/controlpanel.xml
src/collective/cron/profiles/default/metadata.xml
