Metadata-Version: 2.1
Name: collective.cron
Version: 2.8
Summary: Product that enable cron like jobs for plone
Home-page: http://pypi.python.org/pypi/collective.cron
Author: kiorky <kiorky@cryptelium.net>
Author-email: kiorky@cryptelium.com
License: GPL
Platform: UNKNOWN
Classifier: Programming Language :: Python
Classifier: Topic :: Software Development
Provides-Extra: test
